Workbook

Sheet Jan
A1: CV PUTRA BUMI BERKAH
A2: NERACA
A3: 45657
F5: Selisih = | G5: 11449609
D6: Saldo
A7: Aset | D7: IDR | F7: Rincian =
B8: Bank | F8: Pemasukan
C9: 123-0467834 (BCA) | D9: 1.6805354e+08 | F9: laba tgl 31 | G9: 15900000
C10: 735-5917878 (BCA) | D10: 40420364 | F10: bunga rek 7834 | G10: 2028.32
C11: 735-5537889 (BCA) | D11: -2.7346707e+08 | F11: bunga rek 7878 | G11: 608.11
C12: 735-5467899 (BCA) | D12: 2639027 | F12: revisi harga pak arif tgl 30/12 | G12: 2800000
C13: 620801016258532 (BRI) | D13: 10023500 | G13: =SUM(G9:G12) -> 18702636
C14: 058301001067560 (BRI) | D14: 1.1654253e+08 | F14: Pengeluaran
C15: 058301900009562 (BRI) | D15: 321076645 | F15: BI-Fast cv pbb | G15: 2500
C16: 058301909090560 (BRI) | D16: 130317 | F16: bagi hasil pak itak | G16: 5000000
B17: Total Bank | D17: =SUM(D9:D16) -> 3.8541885e+08 | F17: bagi hasil bu tutik | G17: 2250000
F18: pajak bunga rek 7834 | G18: 405.66
B19: Piutang | F19: pajak bunga rek 7878 | G19: 121.62
C20: Customer | D20: 2362409940 | G20: =SUM(G15:G19) -> 7253027.3
C21: Customer ragi | D21: 51770000
C22: Toko putra bumi berkah | D22: 778056500 | F22: Pemasukan - pengeluaran | G22: =G13-G20 -> 11449609
C23: Pak nanok | D23: 25000000
C24: Pak ozi (blitar) | D24: 30000000
C25: Beli aset tanah | D25: 141000000
C26: Beli aset tanah | D26: 145000000
D27: =SUM(D20:D26) -> 3533236440
B29: Ragi
C30: Ragi 180x602500 | D30: 108450000
C31: Ragi 13x602500 | D31: 7832500
D32: =SUM(D30:D31) -> 116282500
B34: Deposit
C35: SGR 9000x8000 | D35: 72000000
D36: =D35 -> 72000000
A38: Hutang
C39: PT Agrico International | D39: 1409300000
C40: PT JPM-ADM Indonesia | D40: 1735392980
C41: PT Terus Makmur Mandiri | D41: 131200000
D42: =SUM(D39:D41) -> 3275892980
A44: Total aset + Piutang - Hutang | D44: =D17+D27+D32+D36-D42 -> 8.3104481e+08
A47: CV PUTRA BUMI BERKAH
A48: NERACA
A49: 45659
F51: Selisih = | G51: =D91-D44 -> 22489392
D52: Saldo
A53: Aset | D53: IDR | F53: Rincian =
B54: Bank | F54: Pemasukan
C55: 123-0467834 (BCA) | D55: 1.4820354e+08 | F55: laba tgl 2 | G55: 24800000
C56: 735-5917878 (BCA) | D56: 97170364 | F56: laba ragi | G56: 337500
C57: 735-5537889 (BCA) | D57: -14998369 | F57: revisi harga pak arif tgl 21/12 | G57: 12900
C58: 735-5467899 (BCA) | D58: -69144973 | F58: saldo bri bisnis bertambah | G58: 1992
C59: 620801016258532 (BRI) | D59: 10023500 | G59: =SUM(G55:G58) -> 25152392
C60: 058301001067560 (BRI) | D60: 1.1654253e+08 | F60: Pengeluaran
C61: 058301900009562 (BRI) | D61: 659633637 | F61: biaya ADM cv pbb & spbb | G61: 60000
C62: 058301909090560 (BRI) | D62: 130317 | F62: biaya kliring cv spbb | G62: 4000
B63: Total Bank | D63: =SUM(D55:D62) -> 9.4756055e+08 | F63: revisi harga pak ramin tgl 26/12 | G63: 1600000
F64: revisi harga pak arif tgl 20/12 | G64: 99000
B65: Piutang | F65: revisi harga nonik kragan tgl 18/12 | G65: 900000
C66: Customer | D66: 1838670140 | G66: =SUM(G61:G65) -> 2663000
C67: Customer ragi | D67: 4395000
C68: Toko putra bumi berkah | D68: 776006500 | F68: Pemasukan - pengeluaran | G68: =G59-G66 -> 22489392
C69: Pak nanok | D69: 25000000
C70: Pak ozi (blitar) | D70: 30000000
C71: Beli aset tanah | D71: 141000000
C72: Beli aset tanah | D72: 145000000
D73: =SUM(D66:D72) -> 2960071640
B75: Ragi
C76: Ragi 165x602500 | D76: 99412500
C77: Ragi 13x602500 | D77: 7832500
D78: =SUM(D76:D77) -> 107245000
B80: Deposit
C81: SGR 9000x8000 | D81: 72000000
C82: Menir gcu 8500x4300 | D82: 36550000
D83: =SUM(D81:D82) -> 108550000
A85: Hutang
C86: PT Agrico International | D86: 1333600000
C87: PT JPM-ADM Indonesia | D87: 1735392980
C88: PT Terus Makmur Mandiri | D88: 200900000
D89: =SUM(D86:D88) -> 3269892980
A91: Total aset + Piutang - Hutang | D91: =D63+D73+D78+D83-D89 -> 8.5353421e+08
A94: CV PUTRA BUMI BERKAH
A95: NERACA
A96: 45660
F98: Selisih = | G98: =D140-D91 -> 5898000
D99: Saldo
A100: Aset | D100: IDR | F100: Rincian =
B101: Bank | F101: Pemasukan
C102: 123-0467834 (BCA) | D102: 1.6680354e+08 | F102: laba tgl 3 + 4 | G102: 18613000
C103: 735-5917878 (BCA) | D103: 1.0161536e+08 | F103: laba ragi | G103: 115000
C104: 735-5537889 (BCA) | D104: 2.1182188e+08 | F104: pot harga FKS | G104: 300000
C105: 735-5467899 (BCA) | D105: 116655027 | G105: =SUM(G102:G104) -> 19028000
C106: 620801016258532 (BRI) | D106: 10023500 | F106: Pengeluaran
C107: 058301001067560 (BRI) | D107: 1.1654253e+08 | F107: revisi harga bu prapti | G107: 5850000
C108: 058301900009562 (BRI) | D108: -1677363 | F108: RTGS bri bisnis | G108: 30000
C109: 058301909090560 (BRI) | D109: 130317 | F109: bagi hasil mb retno | G109: 2250000
B110: Total Bank | D110: =SUM(D102:D109) -> 7.219148e+08 | F110: buka kas | G110: 5000000
G111: =SUM(G107:G110) -> 13130000
B112: Piutang
C113: Customer | D113: 1731745140 | F113: Pemasukan - pengeluaran | G113: =G105-G111 -> 5898000
C114: Customer ragi | D114: 1270000
C115: Toko putra bumi berkah | D115: 627062500
...

Sheet Feb
A1: CV PUTRA BUMI BERKAH
A2: NERACA
A3: 45689
F5: Selisih = | G5: =D47-Jan!D1190 -> -31217414
D6: Saldo
A7: Aset | D7: IDR | F7: Rincian =
B8: Bank | F8: Pemasukan
C9: 123-0467834 (BCA) | D9: 6257030.5 | F9: laba tgl 1 | G9: 16119000
C10: 735-5917878 (BCA) | D10: 74416200 | F10: laba ragi | G10: 190000
C11: 735-5537889 (BCA) | D11: 1.9027659e+08 | F11: bunga individu 7834 | G11: 1562.42
C12: 735-5467899 (BCA) | D12: 3361961 | F12: bunga individu 7878 | G12: 1045.54
C13: 620801016258532 (BRI) | D13: 10885100 | G13: =SUM(G9:G12) -> 16311608
C14: 058301001067560 (BRI) | D14: 29627287 | F14: Pengeluaran
C15: 058301900009562 (BRI) | D15: 120552779 | F15: BI-Fast bri bisnis | G15: 2500
C16: 058301909090560 (BRI) | D16: 130317 | F16: pot harga ko hadi | G16: 900000
B17: Total Bank | D17: =SUM(D9:D16) -> 4.3550727e+08 | F17: bayar BFI & BRI an bayu adi angs ke 14 | G17: 13478500
F18: buka kas | G18: 5000000
B19: Piutang | F19: gaji karyawan januari 2025 | G19: 27700000
C20: Customer | D20: 2716182774 | F20: biaya ADM cv pbb & cv spbb | G20: 60000
C21: Customer ragi | D21: 7680000 | F21: BI-Fast cv pbb | G21: 12500
C22: Toko putra bumi berkah | D22: 902179500 | F22: pajak bunga individu 7834 | G22: 312.48
C23: Pak nanok | D23: 25000000 | F23: pajak bunga individu 7878 | G23: 209.11
C24: Pak ozi (blitar) | D24: 30000000 | F24: selisih harga panah | G24: 375000
C25: Beli aset tanah | D25: 141000000 | G25: =SUM(G15:G24) -> 47529022
C26: Beli aset tanah | D26: 145000000
C27: Pak deny pinjam | D27: 100000000 | F27: Pemasukan - pengeluaran | G27: =G13-G25 -> -31217414
D28: =SUM(D20:D27) -> 4067042274
B30: Ragi
C31: Ragi 46x602500 | D31: 27715000
C32: Ragi 5x602500 | D32: 3012500
D33: =SUM(D31:D32) -> 30727500
B35: Deposit
C36: Tulip 4500x8300 | D36: 37350000
D37: =SUM(D36:D36) -> 37350000
A39: Hutang
C40: PT Agrico International | D40: 1231150000
C41: PT JPM-ADM Indonesia | D41: 1580182000
C42: PT Terus Makmur Mandiri | D42: 206400000
C43: Bu tutik tomat 9000x8450 | D43: 76050000
C44: Cv Maju Terus | D44: 401850000
D45: =SUM(D40:D44) -> 3495632000
A47: Total aset + Piutang - Hutang | D47: =D17+D28+D33+D37-D45 -> 1.074995e+09
A50: CV PUTRA BUMI BERKAH
A51: NERACA
A52: 45691
F54: Selisih = | G54: =D95-D47 -> 26536500
D55: Saldo
A56: Aset | D56: IDR | F56: Rincian =
B57: Bank | F57: Pemasukan
C58: 123-0467834 (BCA) | D58: 1.6510703e+08 | F58: laba tgl 3 | G58: 26110000
C59: 735-5917878 (BCA) | D59: 1.756962e+08 | F59: laba ragi | G59: 515000
C60: 735-5537889 (BCA) | D60: 90091593 | G60: =SUM(G58:G59) -> 26625000
C61: 735-5467899 (BCA) | D61: 130636961 | F61: Pengeluaran
C62: 620801016258532 (BRI) | D62: 10885100 | F62: BI-Fast bri bisnis | G62: 2500
C63: 058301001067560 (BRI) | D63: 29627287 | F63: revisi harga pak arif tgl 20/1 | G63: 86000
C64: 058301900009562 (BRI) | D64: 127225279 | G64: =SUM(G62:G63) -> 88500
C65: 058301909090560 (BRI) | D65: 130317
B66: Total Bank | D66: =SUM(D58:D65) -> 7.2939977e+08 | F66: Pemasukan - pengeluaran | G66: =G60-G64 -> 26536500
B68: Piutang
C69: Customer | D69: 2650290774
C70: Customer ragi | D70: 14145000
C71: Toko putra bumi berkah | D71: 822179500
C72: Pak nanok | D72: 25000000
C73: Pak ozi (blitar) | D73: 30000000
C74: Beli aset tanah | D74: 141000000
C75: Beli aset tanah | D75: 145000000
D76: =SUM(D69:D75) -> 3827615274
B78: Ragi
C79: Ragi 34x602500 | D79: 20485000
C80: Ragi 5x602500 | D80: 3012500
D81: =SUM(D79:D80) -> 23497500
B83: Deposit
C84: Tulip 4500x8300 | D84: 37350000
D85: =SUM(D84:D84) -> 37350000
A87: Hutang
C88: PT Agrico International | D88: 1307200000
C89: PT JPM-ADM Indonesia | D89: 1681181000
C90: PT Terus Makmur Mandiri | D90: 206400000
C91: PT Seger Agro Nusantara | D91: 73600000
C92: Cv Maju Terus | D92: 247950000
D93: =SUM(D88:D92) -> 3516331000
A95: Total aset + Piutang - Hutang | D95: =D66+D76+D81+D85-D93 -> 1.1015315e+09
A98: CV PUTRA BUMI BERKAH
A99: NERACA
A100: 45692
F102: Selisih = | G102: =D141-D95 -> -1929375
D103: Saldo
A104: Aset | D104: IDR | F104: Rincian =
B105: Bank | F105: Pemasukan
C106: 123-0467834 (BCA) | D106: 1.6678016e+08 | F106: laba tgl 4 | G106: 4360000
C107: 735-5917878 (BCA) | D107: 1.816362e+08 | F107: laba ragi | G107: 362500
C108: 735-5537889 (BCA) | D108: 4.7622909e+08 | F108: pot harga SGR tgl 10/1 | G108: 80000
C109: 735-5467899 (BCA) | D109: 84336961 | G109: =SUM(G106:G108) -> 4802500
C110: 620801016258532 (BRI) | D110: 10885100 | F110: Pengeluaran
C111: 058301001067560 (BRI) | D111: 29627287 | F111: BI-Fast bri bisnis | G111: 2500
C112: 058301900009562 (BRI) | D112: 100966779 | F112: BI-Fast cv pbb | G112: 2500
C113: 058301909090560 (BRI) | D113: 130317 | F113: bagi hasil bu tutik | G113: 2250000
B114: Total Bank | D114: =SUM(D106:D113) -> 1.0505919e+09 | F114: pengeluaran lain2 | G114: 4476875
G115: =SUM(G111:G114) -> 6731875
B116: Piutang
...

Sheet Mar
A1: CV PUTRA BUMI BERKAH
A2: NERACA
A3: 45717
F5: Selisih = | G5: =D41-Feb!D1095 -> -34271387
D6: Saldo
A7: Aset | D7: IDR | F7: Rincian =
B8: Bank | F8: Pemasukan
C9: 123-0467834 (BCA) | D9: 78922776 | F9: laba tgl 1 | G9: 8954000
C10: 735-5917878 (BCA) | D10: 95869492 | F10: bu iin bayar lebih timbang tgl 27/2 20x8450 | G10: 169000
C11: 735-5537889 (BCA) | D11: 3.7509458e+08 | F11: bunga rek individu 7834 | G11: 1025.73
C12: 735-5467899 (BCA) | D12: 1054271 | F12: bunga rek individu 7878 | G12: 990.29
C13: 620801016258532 (BRI) | D13: 745200 | G13: =SUM(G9:G12) -> 9125016
C14: 058301001067560 (BRI) | D14: 89648393 | F14: Pengeluaran
C15: 058301900009562 (BRI) | D15: 544812211 | F15: BI-Fast cv pbb | G15: 7500
C16: 058301909090560 (BRI) | D16: 130317 | F16: gaji karyawan februari 25 | G16: 29850000
B17: Total Bank | D17: =SUM(D9:D16) -> 1.1862772e+09 | F17: bayar BFI & BRI an bayu adi angs ke 15 | G17: 13478500
F18: biaya ADM cv pbb & cv spbb | G18: 60000
B19: Piutang | F19: pajak bunga rek individu 7834 | G19: 205.15
C20: Customer | D20: 2793000024 | F20: pajak bunga rek individu 7878 | G20: 198.06
C21: Customer ragi | D21: 60180000 | G21: =SUM(G15:G20) -> 43396403
C22: Toko putra bumi berkah | D22: 814867500
C23: Pak nanok | D23: 25000000 | F23: Pemasukan - pengeluaran | G23: =G13-G21 -> -34271387
C24: Pak ozi (blitar) | D24: 30000000
C25: Beli aset tanah | D25: 141000000
C26: Beli aset tanah | D26: 145000000
C27: Uang cash mas hery | D27: 800000
C28: Dp terop | D28: 10000000
D29: =SUM(D20:D28) -> 4019847524
B31: Ragi
C32: Ragi 106x602500 | D32: 63865000
D33: =D32 -> 63865000
A35: Hutang
C36: PT Agrico International | D36: 2674525000
C37: PT JPM-ADM Indonesia | D37: 1639657500
C38: PT Terus Makmur Mandiri | D38: 75150000
D39: =SUM(D36:D38) -> 4389332500
A41: Total aset + Piutang - Hutang | D41: =D17+D29+D33-D39 -> 8.8065727e+08
A44: CV PUTRA BUMI BERKAH
A45: NERACA
A46: 45719
F48: Selisih = | G48: =D86-D41 -> -2580500
D49: Saldo
A50: Aset | D50: IDR | F50: Rincian =
B51: Bank | F51: Pemasukan
C52: 123-0467834 (BCA) | D52: 1.7203278e+08 | F52: laba tgl 3 | G52: 6929000
C53: 735-5917878 (BCA) | D53: 97849492 | F53: laba ragi | G53: 227500
C54: 735-5537889 (BCA) | D54: 6.0944758e+08 | F54: mb yeni bayar lebih timbang tgl 27/2 | G54: 174000
C55: 735-5467899 (BCA) | D55: 162704271 | F55: revisi harga ragi mb ida | G55: 20000
C56: 620801016258532 (BRI) | D56: 745200 | F56: bu iin bayar lebih timbang tgl 1/3 | G56: 169000
C57: 058301001067560 (BRI) | D57: 89648393 | G57: =SUM(G52:G56) -> 7519500
C58: 058301900009562 (BRI) | D58: 574812211 | F58: Pengeluaran
C59: 058301909090560 (BRI) | D59: 130317 | F59: buka kas | G59: 10000000
B60: Total Bank | D60: =SUM(D52:D59) -> 1.7073702e+09 | F60: revisi harga pak ramin tgl 24/2 | G60: 100000
G61: =SUM(G59:G60) -> 10100000
B62: Piutang
C63: Customer | D63: 3014875024 | F63: Pemasukan - pengeluaran | G63: =G57-G61 -> -2580500
C64: Customer ragi | D64: 62665000
C65: Toko putra bumi berkah | D65: 690697500
C66: Pak nanok | D66: 25000000
C67: Pak ozi (blitar) | D67: 30000000
C68: Beli aset tanah | D68: 141000000
C69: Beli aset tanah | D69: 145000000
C70: Uang cash mas hery | D70: 800000
C71: Dp terop | D71: 10000000
D72: =SUM(D63:D71) -> 4120037524
B74: Ragi
C75: Ragi 88x602500 | D75: 53020000
C76: Ragi 11x602500 | D76: 6627500
D77: =SUM(D75:D76) -> 59647500
A79: Hutang
C80: PT Agrico International | D80: 2829075000
C81: PT JPM-ADM Indonesia | D81: 1798953500
C82: PT Terus Makmur Mandiri | D82: 232450000
C83: Cv Maju Terus | D83: 148500000
D84: =SUM(D80:D83) -> 5008978500
A86: Total aset + Piutang - Hutang | D86: =D60+D72+D77-D84 -> 8.7807677e+08
A89: CV PUTRA BUMI BERKAH
A90: NERACA
A91: 45720
F93: Selisih = | G93: =D131-D86 -> 5387700
D94: Saldo
A95: Aset | D95: IDR | F95: Rincian =
B96: Bank | F96: Pemasukan
C97: 123-0467834 (BCA) | D97: 776076.11 | F97: laba tgl 4 | G97: 8364500
C98: 735-5917878 (BCA) | D98: 1.0996449e+08 | F98: laba ragi | G98: 507500
C99: 735-5537889 (BCA) | D99: 7.3007308e+08 | G99: =SUM(G97:G98) -> 8872000
C100: 735-5467899 (BCA) | D100: 46204271 | F100: Pengeluaran
C101: 620801016258532 (BRI) | D101: 745200 | F101: revisi harga mas naji tgl 1/3 | G101: 1000000
C102: 058301001067560 (BRI) | D102: 89648393 | F102: bagi hasil bu tutik | G102: 2250000
C103: 058301900009562 (BRI) | D103: 273092211 | F103: BI-Fast bri bisnis | G103: 5000
C104: 058301909090560 (BRI) | D104: 130317 | F104: revisi harga pak arif tgl 13/2 | G104: 133300
B105: Total Bank | D105: =SUM(D97:D104) -> 1.250634e+09 | F105: selisih harga panah | G105: 96000
G106: =SUM(G101:G105) -> 3484300
B107: Piutang
C108: Customer | D108: 3179623424 | F108: Pemasukan - pengeluaran | G108: =G99-G106 -> 5387700
C109: Customer ragi | D109: 60095000
C110: Toko putra bumi berkah | D110: 748247500
C111: Pak nanok | D111: 25000000
C112: Pak ozi (blitar) | D112: 30000000
C113: Beli aset tanah | D113: 141000000
...

Sheet Apr
A1: CV PUTRA BUMI BERKAH
A2: NERACA
A3: 45749
F5: Selisih = | G5: =D44-Mar!D1111 -> -5949871.7
D6: Saldo
A7: Aset | D7: IDR | F7: Rincian =
B8: Bank | F8: Pemasukan
C9: 123-0467834 (BCA) | D9: 1.0642059e+08 | F9: laba tgl 2 | G9: 0
C10: 735-5917878 (BCA) | D10: 80129954 | F10: bunga indv 7834 | G10: 833.54
C11: 735-5537889 (BCA) | D11: -1.7949134e+08 | F11: bunga indv 7878 | G11: 576.87
C12: 735-5467899 (BCA) | D12: 342589581 | G12: =SUM(G9:G11) -> 1410.41
C13: 620801016258532 (BRI) | D13: 1605300 | F13: Pengeluaran
C14: 058301001067560 (BRI) | D14: 12895893 | F14: biaya adm cv pbb & spbb | G14: 60000
C15: 058301900009562 (BRI) | D15: -75062562 | F15: DB-Otomatis kliring cv spbb | G15: 6000
C16: 058301909090560 (BRI) | D16: 130317 | F16: THR pak pendik sopir | G16: 1500000
B17: Total Bank | D17: =SUM(D9:D16) -> 2.8921773e+08 | F17: BI-Fast individu | G17: 5000
F18: pengeluaran lain2 | G18: 3380000
B19: Piutang | F19: tambahan THR pak mantri | G19: 1000000
C20: Customer | D20: 2056893450 | F20: pajak bunga indv 7834 | G20: 166.71
C21: Customer ragi | D21: 5890000 | F21: pajak bunga indv 7878 | G21: 115.37
C22: Toko putra bumi berkah | D22: 828493500 | G22: =SUM(G14:G21) -> 5951282.1
C23: Pak nanok | D23: 25000000
C24: Pak ozi (blitar) | D24: 30000000 | F24: Pemasukan - pengeluaran | G24: =G12-G22 -> -5949871.7
C25: Beli aset tanah | D25: 141000000
C26: Beli aset tanah | D26: 145000000
C27: Tukar uang baru | D27: 17000000
C28: Beli truk W 8707 DQ | D28: 160000000
C29: Dp terop | D29: 10000000
D30: =SUM(D20:D29) -> 3419276950
B32: Ragi
C33: Ragi 243x602500 | D33: 146407500
C34: Ragi 2x602500 | D34: 1205000
D35: =SUM(D33:D34) -> 147612500
A37: Hutang
C38: PT Agrico International | D38: 884500000
C39: PT JPM-ADM Indonesia | D39: 1884861500
C40: PT Terus Makmur Mandiri | D40: 313750000
C41: TSC ko tejo 9000x8300 | D41: 74700000
D42: =SUM(D38:D41) -> 3157811500
A44: Total aset + Piutang - Hutang | D44: =D17+D30+D35-D42 -> 6.9829568e+08
A47: CV PUTRA BUMI BERKAH
A48: NERACA
A49: 45750
F51: Selisih = | G51: =D90-D44 -> -473232
D52: Saldo
A53: Aset | D53: IDR | F53: Rincian =
B54: Bank | F54: Pemasukan
C55: 123-0467834 (BCA) | D55: 1.0642059e+08 | F55: laba tgl 3 | G55: 0
C56: 735-5917878 (BCA) | D56: 80129954 | G56: =SUM(G55:G55) -> 0
C57: 735-5537889 (BCA) | D57: -2.9297784e+08 | F57: Pengeluaran
C58: 735-5467899 (BCA) | D58: 92589581 | F58: saldo bri 532 berkurang | G58: 750
C59: 620801016258532 (BRI) | D59: 1604550 | F59: saldo bri 560 berkurang | G59: 472482
C60: 058301001067560 (BRI) | D60: 2.4922341e+08 | G60: =SUM(G58:G59) -> 473232
C61: 058301900009562 (BRI) | D61: 87438
C62: 058301909090560 (BRI) | D62: 130317 | F62: Pemasukan - pengeluaran | G62: =G56-G60 -> -473232
B63: Total Bank | D63: =SUM(D55:D62) -> 2.37208e+08
B65: Piutang
C66: Customer | D66: 1492205950
C67: Customer ragi | D67: 5890000
C68: Toko putra bumi berkah | D68: 828493500
C69: Pak nanok | D69: 25000000
C70: Pak ozi (blitar) | D70: 30000000
C71: Beli aset tanah | D71: 141000000
C72: Beli aset tanah | D72: 145000000
C73: Tukar uang baru | D73: 17000000
C74: Beli truk W 8707 DQ | D74: 160000000
C75: Dp terop | D75: 10000000
D76: =SUM(D66:D75) -> 2854589450
B78: Ragi
C79: Ragi 243x602500 | D79: 146407500
C80: Ragi 2x602500 | D80: 1205000
D81: =SUM(D79:D80) -> 147612500
A83: Hutang
C84: PT Agrico International | D84: 884500000
C85: PT JPM-ADM Indonesia | D85: 1268637500
C86: PT Terus Makmur Mandiri | D86: 313750000
C87: TSC ko tejo 9000x8300 | D87: 74700000
D88: =SUM(D84:D87) -> 2541587500
A90: Total aset + Piutang - Hutang | D90: =D63+D76+D81-D88 -> 6.9782245e+08
A93: CV PUTRA BUMI BERKAH
A94: NERACA
A95: 45751
F97: Selisih = | G97: =D136-D90 -> 5045500
D98: Saldo
A99: Aset | D99: IDR | F99: Rincian =
B100: Bank | F100: Pemasukan
C101: 123-0467834 (BCA) | D101: 16420589 | F101: laba tgl 4 | G101: 18299000
C102: 735-5917878 (BCA) | D102: 80129954 | F102: laba ragi | G102: 225000
C103: 735-5537889 (BCA) | D103: 62293663 | G103: =SUM(G101:G102) -> 18524000
C104: 735-5467899 (BCA) | D104: 10589581 | F104: Pengeluaran
C105: 620801016258532 (BRI) | D105: 1604550 | F105: bayar BFI & BRI an bayu adi angs ke 16 | G105: 13478500
C106: 058301001067560 (BRI) | D106: 1923410.6 | G106: =SUM(G105:G105) -> 13478500
C107: 058301900009562 (BRI) | D107: 421262438
C108: 058301909090560 (BRI) | D108: 130317 | F108: Pemasukan - pengeluaran | G108: =G103-G106 -> 5045500
B109: Total Bank | D109: =SUM(D101:D108) -> 5.943545e+08
B111: Piutang
C112: Customer | D112: 1735605950
C113: Customer ragi | D113: 12140000
C114: Toko putra bumi berkah | D114: 767493500
C115: Pak nanok | D115: 25000000
...

Sheet Mei
A1: CV PUTRA BUMI BERKAH
A2: NERACA
A3: 45779
F5: Selisih = | G5: =D44-Apr!D1172 -> 10101099
D6: Saldo
A7: Aset | D7: IDR | F7: Rincian =
B8: Bank | F8: Pemasukan
C9: 123-0467834 (BCA) | D9: 3213468.8 | F9: laba tgl 2 + 3 | G9: 28347000
C10: 735-5917878 (BCA) | D10: 1.6505014e+08 | F10: laba ragi | G10: 135000
C11: 735-5537889 (BCA) | D11: -4.1276642e+08 | F11: pak yoyok bayar lebih timbang tgl 30/4 | G11: 191000
C12: 735-5467899 (BCA) | D12: 237896 | F12: bunga rek 7878 | G12: 861.44
C13: 620801016258532 (BRI) | D13: 24250 | F13: bunga rek 7834 | G13: 1099.82
C14: 058301001067560 (BRI) | D14: 1.1400357e+08 | G14: =SUM(G9:G13) -> 28674961
C15: 058301900009562 (BRI) | D15: -135705867 | F15: Pengeluaran
C16: 058301909090560 (BRI) | D16: 130317 | F16: biaya adm cv spbb & pbb | G16: 60000
B17: Total Bank | D17: =SUM(D9:D16) -> -2.6581264e+08 | F17: RTGS bri bisnis | G17: 30000
F18: bayar BFI & BRI an bayu adi angs ke 17 | G18: 13478500
B19: Piutang | F19: biaya kliring | G19: 2000
C20: Customer | D20: 2875016525 | F20: pajak bunga rek 7878 | G20: 172.29
C21: Customer ragi | D21: 6400000 | F21: pajak bunga rek 7834 | G21: 219.96
C22: Toko putra bumi berkah | D22: 792234500 | F22: qris terpotong | G22: 2970
C23: Pak nanok | D23: 25000000 | F23: buka kas | G23: 5000000
C24: Pak ozi (blitar) | D24: 30000000 | G24: =SUM(G16:G23) -> 18573862
C25: Beli aset tanah | D25: 141000000
C26: Beli aset tanah | D26: 145000000 | F26: Pemasukan - pengeluaran | G26: =G14-G24 -> 10101099
C27: Pak budi pinjam | D27: 55000000
C28: Deposit PT Terus Makmur Mandiri | D28: 94500000
C29: Stock BW di gudang | D29: 79650000
C30: Uang cash mas heri | D30: 1660000
D31: =SUM(D20:D30) -> 4245461025
B33: Ragi
C34: Ragi 121x602500 | D34: 72902500
C35: Ragi 5x602500 | D35: 3012500
D36: =SUM(D34:D35) -> 75915000
A38: Hutang
C39: PT Agrico International | D39: 1216700000
C40: PT JPM-ADM Indonesia | D40: 1420726000
C41: DO bw bu tutik | D41: 14250000
D42: =SUM(D39:D41) -> 2651676000
A44: Total aset + Piutang - Hutang | D44: =D17+D31+D36-D42 -> 1.4038874e+09
A47: CV PUTRA BUMI BERKAH
A48: NERACA
A49: 45780
F51: Selisih = | G51: =D89-D44 -> 7511530
D52: Saldo
A53: Aset | D53: IDR | F53: Rincian =
B54: Bank | F54: Pemasukan
C55: 123-0467834 (BCA) | D55: 16038469 | F55: laba tgl 3 | G55: 4877000
C56: 735-5917878 (BCA) | D56: 1.6505014e+08 | F56: laba ragi | G56: 2637500
C57: 735-5537889 (BCA) | D57: -5.1329142e+08 | G57: =SUM(G55:G56) -> 7514500
C58: 735-5467899 (BCA) | D58: 1062896 | F58: Pengeluaran
C59: 620801016258532 (BRI) | D59: 24250 | F59: qris terpotong | G59: 2970
C60: 058301001067560 (BRI) | D60: 1.1535357e+08 | G60: =SUM(G59:G59) -> 2970
C61: 058301900009562 (BRI) | D61: -18168837
C62: 058301909090560 (BRI) | D62: 130317 | F62: Pemasukan - pengeluaran | G62: =G57-G60 -> 7511530
B63: Total Bank | D63: =SUM(D55:D62) -> -2.3380061e+08
B65: Piutang
C66: Customer | D66: 3135991525
C67: Customer ragi | D67: 60250000
C68: Toko putra bumi berkah | D68: 809719500
C69: Pak nanok | D69: 25000000
C70: Pak ozi (blitar) | D70: 30000000
C71: Beli aset tanah | D71: 141000000
C72: Beli aset tanah | D72: 145000000
C73: Pak budi pinjam | D73: 55000000
C74: Deposit PT Terus Makmur Mandiri | D74: 13500000
C75: Stock BW di gudang | D75: 79650000
C76: Uang cash mas heri | D76: 2160000
D77: =SUM(D66:D76) -> 4497271025
B79: Ragi
C80: Ragi 36x602500 | D80: 21690000
C81: Ragi 5x602500 | D81: 3012500
D82: =SUM(D80:D81) -> 24702500
A84: Hutang
C85: PT Agrico International | D85: 1216700000
C86: PT JPM-ADM Indonesia | D86: 1660074000
D87: =SUM(D85:D86) -> 2876774000
A89: Total aset + Piutang - Hutang | D89: =D63+D77+D82-D87 -> 1.4113989e+09
A92: CV PUTRA BUMI BERKAH
A93: NERACA
A94: 45782
F96: Selisih = | G96: =D136-D89 -> 21630030
D97: Saldo
A98: Aset | D98: IDR | F98: Rincian =
B99: Bank | F99: Pemasukan
C100: 123-0467834 (BCA) | D100: 2988468.8 | F100: laba tgl 5 + 6 | G100: 23584000
C101: 735-5917878 (BCA) | D101: 1.7165014e+08 | F101: laba ragi | G101: 115000
C102: 735-5537889 (BCA) | D102: -6.5010142e+08 | F102: mb yeni bayar lebih timbang tgl 21/4 | G102: 189000
C103: 735-5467899 (BCA) | D103: 2862896 | G103: =SUM(G100:G102) -> 23888000
C104: 620801016258532 (BRI) | D104: 24250 | F104: Pengeluaran
C105: 058301001067560 (BRI) | D105: 1.1535357e+08 | F105: bagi hasil mb retno | G105: 2250000
C106: 058301900009562 (BRI) | D106: 16953193 | F106: BI-Fast bri bisnis | G106: 5000
C107: 058301909090560 (BRI) | D107: 130317 | F107: qris terpotong | G107: 2970
B108: Total Bank | D108: =SUM(D100:D107) -> -3.4013858e+08 | G108: =SUM(G105:G107) -> 2257970
B110: Piutang | F110: Pemasukan - pengeluaran | G110: =G103-G108 -> 21630030
C111: Customer | D111: 3146926525
C112: Customer ragi | D112: 54970000
C113: Toko putra bumi berkah | D113: 796041500
C114: Pak nanok | D114: 25000000
C115: Pak ozi (blitar) | D115: 30000000
...

Sheet Juni
A1: CV PUTRA BUMI BERKAH
A2: NERACA
A3: 45810
F5: Selisih = | G5: =D44-Mei!D1107 -> -18900970
D6: Saldo
A7: Aset | D7: IDR | F7: Rincian =
B8: Bank | F8: Pemasukan
C9: 123-0467834 (BCA) | D9: 1.1110809e+08 | F9: laba tgl 2 | G9: 2922000
C10: 735-5917878 (BCA) | D10: 39938299 | F10: laba ragi | G10: 375000
C11: 735-5537889 (BCA) | D11: 4.0663301e+08 | F11: bunga rek indv 7878 | G11: 819.33
C12: 735-5467899 (BCA) | D12: 90506 | F12: bunga rek indv 7834 | G12: 1093.42
C13: 620801016258532 (BRI) | D13: 16250 | G13: =SUM(G9:G12) -> 3298912.8
C14: 058301001067560 (BRI) | D14: 1.4991665e+08 | F14: Pengeluaran
C15: 058301900009562 (BRI) | D15: -42077063 | F15: adm kliring cv surya | G15: 6000
C16: 058301909090560 (BRI) | D16: 130317 | F16: biaya adm cv spbb + cv pbb | G16: 60000
B17: Total Bank | D17: =SUM(D9:D16) -> 6.6575606e+08 | F17: pajak bunga rek indv 7878 | G17: 163.87
F18: pajak bunga rek indv 7834 | G18: 218.68
B19: Piutang | F19: BI-Fast bri bisnis | G19: 5000
C20: Customer | D20: 3238321505 | F20: angs bri unit ke 1 an bayu adi | G20: 14550000
C21: Customer ragi | D21: 12355000 | F21: angs BFI ke 18 an bayu adi | G21: 7578500
C22: Toko putra bumi berkah | D22: 957417500 | G22: =SUM(G15:G21) -> 22199883
C23: Pak nanok | D23: 25000000
C24: Pak ozi (blitar) | D24: 30000000 | F24: Pemasukan - pengeluaran | G24: =G13-G22 -> -18900970
C25: Beli aset tanah | D25: 141000000
C26: Beli aset tanah | D26: 145000000
C27: Pak budi pinjam | D27: 100000000
C28: Beli truk S 9344 ND + K 8094 IS | D28: 155002500
C29: Dp mobil fortuner | D29: 156395550
C30: Deposit di TMM | D30: 60125000
D31: =SUM(D20:D30) -> 5020617055
B33: Ragi
C34: Ragi 229x602500 | D34: =229*602500 -> 137972500
C35: Ragi 6x602500 | D35: =6*602500 -> 3615000
D36: =SUM(D34:D35) -> 141587500
A38: Hutang
C39: PT Agrico International | D39: 2301300000
C40: PT JPM-ADM Indonesia | D40: 1768305000
C41: Cv Maju Terus | D41: 174800000
D42: =SUM(D39:D41) -> 4244405000
A44: Total aset + Piutang - Hutang | D44: =D17+D31+D36-D42 -> 1.5835556e+09
A47: CV PUTRA BUMI BERKAH
A48: NERACA
A49: 45811
F51: Selisih = | G51: =D92-D44 -> -13815600
D52: Saldo
A53: Aset | D53: IDR | F53: Rincian =
B54: Bank | F54: Pemasukan
C55: 123-0467834 (BCA) | D55: 88185588 | F55: laba tgl 3 | G55: 2889000
C56: 735-5917878 (BCA) | D56: 39938299 | F56: laba ragi | G56: 115000
C57: 735-5537889 (BCA) | D57: 9.0189941e+08 | F57: pak yoyok bayar lebih timbang panah tgl 2/6 | G57: 189000
C58: 735-5467899 (BCA) | D58: 1290506 | G58: =SUM(G55:G57) -> 3193000
C59: 620801016258532 (BRI) | D59: 16250 | F59: Pengeluaran
C60: 058301001067560 (BRI) | D60: 2914148.6 | F60: bagi hasil bu tutik | G60: 2250000
C61: 058301900009562 (BRI) | D61: -13828563 | F61: bayar lebih timbang panah | G61: 9528600
C62: 058301909090560 (BRI) | D62: 130317 | F62: BI-Fast bri 560 | G62: 2500
B63: Total Bank | D63: =SUM(D55:D62) -> 1.020546e+09 | F63: BI-Fast bri bisnis | G63: 2500
F64: buka kas | G64: 5000000
B65: Piutang | F65: revisi harga jempol sip abah slamet tgl 30/5 | G65: 225000
C66: Customer | D66: 2805931505 | G66: =SUM(G60:G65) -> 17008600
C67: Customer ragi | D67: 13675000
C68: Toko putra bumi berkah | D68: 826536500 | F68: Pemasukan - pengeluaran | G68: =G58-G66 -> -13815600
C69: Pak nanok | D69: 25000000
C70: Pak ozi (blitar) | D70: 30000000
C71: Beli aset tanah | D71: 141000000
C72: Beli aset tanah | D72: 145000000
C73: Pak budi pinjam | D73: 100000000
C74: Beli truk S 9344 ND + K 8094 IS | D74: 155002500
C75: Dp mobil fortuner | D75: 156395550
C76: Beli L300 L 8921 AAD | D76: 103002500
C77: Deposit di TMM | D77: 60125000
D78: =SUM(D66:D77) -> 4561668555
B80: Ragi
C81: Ragi 223x602500 | D81: =223*602500 -> 134357500
C82: Ragi 4x602500 | D82: =4*602500 -> 2410000
C83: Ragi 6x602500 | D83: =6*602500 -> 3615000
D84: =SUM(D81:D83) -> 140382500
A86: Hutang
C87: PT Agrico International | D87: 2554500000
C88: PT JPM-ADM Indonesia | D88: 1515557000
C89: Cv Maju Terus | D89: 82800000
D90: =SUM(D87:D89) -> 4152857000
A92: Total aset + Piutang - Hutang | D92: =D63+D78+D84-D90 -> 1.56974e+09
A95: CV PUTRA BUMI BERKAH
A96: NERACA
A97: 45812
F99: Selisih = | G99: =D141-D92 -> 12837300
D100: Saldo
A101: Aset | D101: IDR | F101: Rincian =
B102: Bank | F102: Pemasukan
C103: 123-0467834 (BCA) | D103: 1.7925559e+08 | F103: laba tgl 4 + 5 | G103: 14475000
C104: 735-5917878 (BCA) | D104: 39938299 | F104: laba ragi | G104: 475000
C105: 735-5537889 (BCA) | D105: -2.0515529e+08 | F105: pak yoyok bayar lebih timbang panah tgl 3/6 | G105: 189000
C106: 735-5467899 (BCA) | D106: 3163506 | G106: =SUM(G103:G105) -> 15139000
C107: 620801016258532 (BRI) | D107: 16250 | F107: Pengeluaran
C108: 058301001067560 (BRI) | D108: 2914148.6 | F108: BI-Fast bri bisnis | G108: 2500
C109: 058301900009562 (BRI) | D109: -44356063 | F109: revisi harga pak arif tgl 26/5 | G109: 223200
C110: 058301909090560 (BRI) | D110: 130317 | F110: fee tumpi pak itak | G110: 1576000
B111: Total Bank | D111: =SUM(D103:D110) -> -24093241 | F111: fee tumpi ardi gudang | G111: 500000
G112: =SUM(G108:G111) -> 2301700
B113: Piutang
...

Sheet Juli
A1: CV PUTRA BUMI BERKAH
A2: NERACA
A3: 45839
F5: Selisih = | G5: =D49-Juni!D1133 -> -1.0025335e+08
D6: Saldo
A7: Aset | D7: IDR | F7: Rincian =
B8: Bank | F8: Pemasukan
C9: 123-0467834 (BCA) | D9: 2.0009422e+08 | F9: laba tgl 1 | G9: -4966000
C10: 735-5917878 (BCA) | D10: 1.0885379e+08 | F10: bunga rek indv 7878 | G10: 610.67
C11: 735-5537889 (BCA) | D11: 1.6046906e+08 | F11: bunga rek indv 7834 | G11: 1450.46
C12: 735-5467899 (BCA) | D12: 17952116 | G12: =SUM(G9:G11) -> -4963938.9
C13: 620801016258532 (BRI) | D13: 8250 | F13: Pengeluaran
C14: 058301001067560 (BRI) | D14: 894733.6 | F14: biaya adm kliring cv spbb | G14: 6000
C15: 058301900009562 (BRI) | D15: 14012245 | F15: biaya adm cv pbb & spbb | G15: 60000
C16: 058301909090560 (BRI) | D16: 130317 | F16: bagi hasil bu tutik | G16: 2250000
B17: Total Bank | D17: =SUM(D9:D16) -> 5.0241472e+08 | F17: BI-Fast cv pbb | G17: 10000
F18: gaji karyawan bulan juni 2025 | G18: 30350000
B19: Piutang | F19: angs bri unit ke 2 an bayu adi | G19: 14550000
C20: Customer | D20: 3246817605 | F20: angs BFI ke 19 an bayu adi | G20: 7578500
C21: Customer ragi | D21: 14000000 | F21: angs BFI ke 1 an suryo hadi | G21: 11503000
C22: Toko putra bumi berkah | D22: 872103000 | F22: angs TAF ke 1 an suryo hadi | G22: 23975000
C23: Toko putra bumi berkah blitar | D23: 219033000 | F23: biaya adm tf ke bank lain cv pbb | G23: 6500
C24: Pak nanok | D24: 25000000 | F24: pajak bunga rek indv 7878 | G24: 122.13
C25: Pak ozi (blitar) | D25: 30000000 | F25: pajak bunga rek indv 7834 | G25: 290.09
C26: Beli aset tanah | D26: 141000000 | F26: buka kas | G26: 5000000
C27: Beli aset tanah | D27: 145000000 | G27: =SUM(G14:G26) -> 95289412
C28: Pak budi pinjam | D28: 100000000
C29: Beli truk S 9344 ND + K 8094 IS | D29: 180880000 | F29: Pemasukan - pengeluaran | G29: =G12-G27 -> -1.0025335e+08
C30: Dp mobil fortuner | D30: 156395550
C31: Pembayaran tanah | D31: 304750000
C32: Bapak pinjam dari rek bri 560 | D32: 1185745
C33: Angkutan pinjam bri 560 | D33: 1002500
C34: Angkutan pinjam rek ragi | D34: 15002500
C35: Deposit di TMM | D35: 60125000
D36: =SUM(D20:D35) -> 5512294900
B38: Ragi
C39: Ragi 59x602500 | D39: =59*602500 -> 35547500
C40: Ragi 1x602500 | D40: =1*602500 -> 602500
D41: =SUM(D39:D40) -> 36150000
A43: Hutang
C44: PT Agrico International | D44: 2896900000
C45: PT JPM-ADM Indonesia | D45: 1657351000
C46: PT Kabulinco Jaya | D46: 88000000
D47: =SUM(D44:D46) -> 4642251000
A49: Total aset + Piutang - Hutang | D49: =D17+D36+D41-D47 -> 1.4086086e+09
A52: CV PUTRA BUMI BERKAH
A53: NERACA
A54: 45840
F56: Selisih = | G56: =D100-D49 -> -7609000
D57: Saldo
A58: Aset | D58: IDR | F58: Rincian =
B59: Bank | F59: Pemasukan
C60: 123-0467834 (BCA) | D60: 51094219 | F60: laba tgl 2 + 3 | G60: -6744000
C61: 735-5917878 (BCA) | D61: 1.1149379e+08 | F61: laba ragi | G61: 137500
C62: 735-5537889 (BCA) | D62: 1.1730206e+08 | G62: =SUM(G60:G61) -> -6606500
C63: 735-5467899 (BCA) | D63: 10952116 | F63: Pengeluaran
C64: 620801016258532 (BRI) | D64: 8250 | F64: revisi harga hiu mb yeni tgl 30/6 | G64: 1000000
C65: 058301001067560 (BRI) | D65: 894733.6 | F65: BI-Fast bri bisnis | G65: 2500
C66: 058301900009562 (BRI) | D66: -7259255 | G66: =SUM(G64:G65) -> 1002500
C67: 058301909090560 (BRI) | D67: 130317
B68: Total Bank | D68: =SUM(D60:D67) -> 2.8461622e+08 | F68: Pemasukan - pengeluaran | G68: =G62-G66 -> -7609000
B70: Piutang
C71: Customer | D71: 2659577605
C72: Customer ragi | D72: 14510000
C73: Toko putra bumi berkah | D73: 783372000
C74: Toko putra bumi berkah blitar | D74: 199133000
C75: Pak nanok | D75: 25000000
C76: Pak ozi (blitar) | D76: 30000000
C77: Beli aset tanah | D77: 141000000
C78: Beli aset tanah | D78: 145000000
C79: Pak budi pinjam | D79: 100000000
C80: Beli truk S 9344 ND + K 8094 IS | D80: 180880000
C81: Dp mobil fortuner | D81: 156395550
C82: Pembayaran tanah | D82: 304750000
... C86: Deposit di TMM | D86: 60125000
D87: =SUM(D71:D86) -> 4816933900
B89: Ragi
C90: Ragi 54x602500 | D90: =54*602500 -> 32535000
C91: Ragi 1x602500 | D91: =1*602500 -> 602500
D92: =SUM(D90:D91) -> 33137500
A94: Hutang
C95: PT Agrico International | D95: 1826650000
C96: PT JPM-ADM Indonesia | D96: 1819038000
C97: PT Kabulinco Jaya | D97: 88000000
D98: =SUM(D95:D97) -> 3733688000
A100: Total aset + Piutang - Hutang | D100: =D68+D87+D92-D98 -> 1.4009996e+09
A103: CV PUTRA BUMI BERKAH
A104: NERACA
A105: 45841
F107: Selisih = | G107: =D150-D100 -> -26818750
D108: Saldo
A109: Aset | D109: IDR | F109: Rincian =
B110: Bank | F110: Pemasukan
C111: 123-0467834 (BCA) | D111: -905781.09 | F111: laba tgl 3 | G111: -3238000
C112: 735-5917878 (BCA) | D112: 1.2473379e+08 | F112: laba ragi | G112: 115000
C113: 735-5537889 (BCA) | D113: 2.2855206e+08 | F113: selisih harga panah | G113: 2564250
C114: 735-5467899 (BCA) | D114: -80947884 | G114: =SUM(G111:G113) -> -558750
C115: 620801016258532 (BRI) | D115: 8250 | F115: Pengeluaran
C116: 058301001067560 (BRI) | D116: 642233.6 | F116: BI-Fast bri bisnis | G116: 7500
C117: 058301900009562 (BRI) | D117: -157696755 | F117: gaji mb nayla bulan juli 2025 | G117: 3000000
...

Sheet Agust
A1: CV PUTRA BUMI BERKAH
A2: NERACA
A3: 45870
F5: Selisih = | G5: =D43-Juli!D1312 -> -77545351
D6: Saldo
A7: Aset | D7: IDR | F7: Rincian =
B8: Bank | F8: Pemasukan
C9: 123-0467834 (BCA) | D9: 1.0137291e+08 | F9: laba tgl 1 | G9: 2744000
C10: 735-5917878 (BCA) | D10: 1.6655227e+08 | F10: pak sukem bayar lebih timbang tgl 23/7 | G10: 178000
C11: 735-5537889 (BCA) | D11: 2.1582998e+08 | F11: bunga rek indv 7878 | G11: 1224.03
C12: 735-5467899 (BCA) | D12: 5993726 | F12: bunga rek indv 7834 | G12: 837.8
C13: 620801016258532 (BRI) | D13: 2450083.6 | G13: =SUM(G9:G12) -> 2924061.8
C14: 058301001067560 (BRI) | D14: 873247 | F14: Pengeluaran
C15: 058301900009562 (BRI) | D15: 376452126 | F15: gaji karyawan bulan juli 2025 | G15: 31350000
C16: 058301909090560 (BRI) | D16: 130317 | F16: BI-fast cv putra | G16: 7500
B17: Total Bank | D17: =SUM(D9:D16) -> 8.6965466e+08 | F17: biaya adm cv pbb & cv spbb | G17: 60000
F18: biaya kliring cv spbb | G18: 2000
B19: Piutang | F19: angs bri unit ke 3 an bayu adi | G19: 14550000
C20: Customer | D20: 2428442137 | F20: angs BFI ke 20 an bayu adi | G20: 7578500
C21: Customer ragi | D21: 13465000 | F21: angs BFI ke 2 an suryo hadi | G21: 11503000
C22: Toko putra bumi berkah | D22: 1035510838 | F22: angs trihamas ke 1 an suryo hadi | G22: 10418000
C23: Toko putra blitar | D23: 463050000 | F23: pajak bunga rek indv 7878 | G23: 244.81
C24: Pak nanok | D24: 25000000 | F24: pajak bunga rek indv 7834 | G24: 167.56
C25: Pak ozi (blitar) | D25: 30000000 | F25: buka kas | G25: 5000000
C26: Pak budi pinjam | D26: 50000000 | G26: =SUM(G15:G25) -> 80469412
C27: Angkutan pinjam bri 560 | D27: 1002500
C28: Angkutan pinjam rek ragi | D28: 50005000 | F28: Pemasukan - pengeluaran | G28: =G13-G26 -> -77545351
D29: =SUM(D20:D28) -> 4096475475
B31: Ragi
C32: Ragi 296x602500 | D32: =296*602500 -> 178340000
C33: Ragi 6x602500 | D33: =6*602500 -> 3615000
C34: Ragi 4x602500 | D34: =4*602500 -> 2410000
D35: =SUM(D32:D34) -> 184365000
A37: Hutang
C38: PT Agrico International | D38: 2182050000
C39: PT JPM-ADM Indonesia | D39: 1465749030
C40: Cv Maju Terus | D40: 227475000
D41: =SUM(D38:D40) -> 3875274030
A43: Total aset + Piutang - Hutang | D43: =D17+D29+D35-D41 -> 1.2752211e+09
A46: CV PUTRA BUMI BERKAH
A47: NERACA
A48: 45871
F50: Selisih = | G50: =D88-D43 -> -19121500
D51: Saldo
A52: Aset | D52: IDR | F52: Rincian =
B53: Bank | F53: Pemasukan
C54: 123-0467834 (BCA) | D54: 1.7877291e+08 | F54: laba tgl 2 | G54: 4860000
C55: 735-5917878 (BCA) | D55: 1.6655227e+08 | G55: =SUM(G54:G54) -> 4860000
C56: 735-5537889 (BCA) | D56: 4.2719848e+08 | F56: Pengeluaran
C57: 735-5467899 (BCA) | D57: 3543726 | F57: angs TAF ke 2 an suryo hadi | G57: 23975000
C58: 620801016258532 (BRI) | D58: 2450083.6 | F58: biaya adm tf ke bank lain | G58: 6500
C59: 058301001067560 (BRI) | D59: 873247 | G59: =SUM(G57:G58) -> 23981500
C60: 058301900009562 (BRI) | D60: 461952126
C61: 058301909090560 (BRI) | D61: 130317 | F61: Pemasukan - pengeluaran | G61: =G55-G59 -> -19121500
B62: Total Bank | D62: =SUM(D54:D61) -> 1.2414732e+09
B64: Piutang
C65: Customer | D65: 2360042137
C66: Customer ragi | D66: 13465000
C67: Toko putra bumi berkah | D67: 1061310838
C68: Toko putra blitar | D68: 463050000
C69: Pak nanok | D69: 25000000
C70: Pak ozi (blitar) | D70: 30000000
C71: Pak budi pinjam | D71: 50000000
C72: Angkutan pinjam bri 560 | D72: 1002500
C73: Angkutan pinjam rek ragi | D73: 50005000
D74: =SUM(D65:D73) -> 4053875475
B76: Ragi
C77: Ragi 296x602500 | D77: =296*602500 -> 178340000
C78: Ragi 6x602500 | D78: =6*602500 -> 3615000
C79: Ragi 4x602500 | D79: =4*602500 -> 2410000
D80: =SUM(D77:D79) -> 184365000
A82: Hutang
C83: PT Agrico International | D83: 2368725000
C84: PT JPM-ADM Indonesia | D84: 1551589030
C85: Cv Maju Terus | D85: 303300000
D86: =SUM(D83:D85) -> 4223614030
A88: Total aset + Piutang - Hutang | D88: =D62+D74+D80-D86 -> 1.2560996e+09
A91: CV PUTRA BUMI BERKAH
A92: NERACA
A93: 45873
F95: Selisih = | G95: =D134-D88 -> 1043000
D96: Saldo
A97: Aset | D97: IDR | F97: Rincian =
B98: Bank | F98: Pemasukan
C99: 123-0467834 (BCA) | D99: 1.7877291e+08 | F99: laba tgl 4 | G99: 5753000
C100: 735-5917878 (BCA) | D100: 1.7297727e+08 | F100: laba ragi | G100: 292500
C101: 735-5537889 (BCA) | D101: 1.6388281e+08 | G101: =SUM(G99:G100) -> 6045500
C102: 735-5467899 (BCA) | D102: 90243726 | F102: Pengeluaran
C103: 620801016258532 (BRI) | D103: 2450083.6 | F103: BI-Fast bri bisnis | G103: 2500
C104: 058301001067560 (BRI) | D104: 873247 | F104: buka kas | G104: 5000000
C105: 058301900009562 (BRI) | D105: 413743626 | G105: =SUM(G103:G104) -> 5002500
C106: 058301909090560 (BRI) | D106: 130317
B107: Total Bank | D107: =SUM(D99:D106) -> 1.023074e+09 | F107: Pemasukan - pengeluaran | G107: =G101-G105 -> 1043000
B109: Piutang
C110: Customer | D110: 2766392137
C111: Customer ragi | D111: 12755000
C112: Toko putra bumi berkah | D112: 980566838
C113: Toko putra blitar | D113: 539550000
C114: Pak nanok | D114: 25000000
C115: Pak ozi (blitar) | D115: 30000000
...

Sheet Sept
A1: CV PUTRA BUMI BERKAH
A2: NERACA
A3: 45901
F5: Selisih = | G5: =D46-Agust!D1209 -> -19908122
D6: Saldo
A7: Aset | D7: IDR | F7: Rincian =
B8: Bank | F8: Pemasukan
C9: 123-0467834 (BCA) | D9: 1.0635299e+08 | F9: laba tgl 1 | G9: 18188000
C10: 735-5917878 (BCA) | D10: 37173580 | F10: laba ragi | G10: 252500
C11: 735-5537889 (BCA) | D11: 1.5958453e+08 | F11: bunga rek indv 7834 | G11: 983.57
C12: 735-5467899 (BCA) | D12: 224967511 | F12: bunga rek indv 7878 | G12: 1641.96
C13: 620801016258532 (BRI) | D13: 25000 | G13: =SUM(G9:G12) -> 18443126
C14: 058301001067560 (BRI) | D14: 17233024 | F14: Pengeluaran
C15: 058301900009562 (BRI) | D15: 315736929 | F15: BI-Fast bri 560 | G15: 2500
C16: 058301909090560 (BRI) | D16: 130317 | F16: gaji karyawan bulan agustus 2025 | G16: 36850000
B17: Total Bank | D17: =SUM(D9:D16) -> 8.6120389e+08 | F17: pajak bunga rek indv 7834 | G17: 196.71
F18: pajak bunga rek indv 7878 | G18: 328.39
B19: Piutang | F19: biaya adm rek cv spbb & pbb | G19: 60000
C20: Customer | D20: 2371714637 | F20: BI-Fast rek indv 7878 | G20: 5000
C21: Customer ragi | D21: 24705000 | F21: angs BRI bisnis ? | G21: 1229772
C22: Toko putra bumi berkah | D22: 910182838 | F22: revisi harga pak arif tgl 31/7 | G22: 114450
C23: Toko putra blitar | D23: 530100000 | F23: revisi harga pak arif tgl 13/8 | G23: 84000
C24: Pak nanok | D24: 25000000 | F24: BI-Fast cv pbb | G24: 2500
C25: Pak ozi (blitar) | D25: 30000000 | F25: BI-Fast bri bisnis | G25: 2500
C26: Pak budi pinjam | D26: 50000000 | G26: =SUM(G15:G25) -> 38351247
C27: Bayar kontrak blitar | D27: 33000000
C28: Beli truk pak hasan W 8358 NZ | D28: 180000000 | F28: Pemasukan - pengeluaran | G28: =G13-G26 -> -19908122
C29: Angkutan pinjam bri 560 | D29: 1002500
C30: Angkutan pinjam rek ragi | D30: 50005000
D31: =SUM(D20:D30) -> 4205709975
B33: Ragi
C34: Ragi 198x602500 | D34: =198*602500 -> 119295000
C35: Ragi 9x602500 | D35: =9*602500 -> 5422500
C36: Ragi 0x602500 | D36: 0
D37: =SUM(D34:D36) -> 124717500
A39: Hutang
C40: PT Agrico International | D40: 1963100000
C41: PT JPM-ADM Indonesia | D41: 1561401500
C42: PT Kabulinco Jaya | D42: 336000000
C43: PT Terus Makmur Mandiri | D43: 25200000
D44: =SUM(D40:D43) -> 3885701500
A46: Total aset + Piutang - Hutang | D46: =D17+D31+D37-D44 -> 1.3059299e+09
A49: CV PUTRA BUMI BERKAH
A50: NERACA
A51: 45902
F53: Selisih = | G53: =D94-D46 -> -89972000
D54: Saldo
A55: Aset | D55: IDR | F55: Rincian =
B56: Bank | F56: Pemasukan
C57: 123-0467834 (BCA) | D57: 1.9025299e+08 | F57: laba tgl 2 | G57: 5210000
C58: 735-5917878 (BCA) | D58: 43473580 | F58: laba ragi | G58: 225000
C59: 735-5537889 (BCA) | D59: 3.2693003e+08 | G59: =SUM(G57:G58) -> 5435000
C60: 735-5467899 (BCA) | D60: -22482489 | F60: Pengeluaran
C61: 620801016258532 (BRI) | D61: 25000 | F61: angs BFI ke 21 an bayu adi | G61: 7578500
C62: 058301001067560 (BRI) | D62: 17233024 | F62: angs BFI ke 3 an suryo hadi (L300) | G62: 11503000
C63: 058301900009562 (BRI) | D63: 51184429 | F63: angs BFI ke 2 an suryo hadi (A 8379 CO) | G63: 24923500
C64: 058301909090560 (BRI) | D64: 130317 | F64: angs trihamas ke 2 an suryo hadi | G64: 10418000
B65: Total Bank | D65: =SUM(D57:D64) -> 6.0674689e+08 | F65: angs BRI ke 4 an bayu adi | G65: 14550000
F66: angs TAF ke 3 an suryo hadi | G66: 23975000
B67: Piutang | F67: biaya adm tf ke bank lain | G67: 6500
C68: Customer | D68: 2171314637 | F68: revisi harga pak ramin tgl 19 & 22/8 | G68: 200000
C69: Customer ragi | D69: 24655000 | F69: bagi hasil bu tutik | G69: 2250000
C70: Toko putra bumi berkah | D70: 910182838 | F70: BI-Fast bri bisnis | G70: 2500
C71: Toko putra blitar | D71: 452700000 | G71: =SUM(G61:G70) -> 95407000
C72: Pak nanok | D72: 25000000
C73: Pak ozi (blitar) | D73: 30000000 | F73: Pemasukan - pengeluaran | G73: =G59-G71 -> -89972000
C74: Pak budi pinjam | D74: 50000000
C75: Bayar kontrak blitar | D75: 33000000
C76: Beli truk pak hasan W 8358 NZ | D76: 180000000
C77: Angkutan pinjam bri 560 | D77: 1002500
C78: Angkutan pinjam rek ragi | D78: 50005000
D79: =SUM(D68:D78) -> 3927859975
B81: Ragi
C82: Ragi 188x602500 | D82: =188*602500 -> 113270000
C83: Ragi 9x602500 | D83: =9*602500 -> 5422500
C84: Ragi 0x602500 | D84: 0
D85: =SUM(D82:D84) -> 118692500
A87: Hutang
C88: PT Agrico International | D88: 1345650000
C89: PT JPM-ADM Indonesia | D89: 1646491500
C90: PT Kabulinco Jaya | D90: 336000000
C91: PT Terus Makmur Mandiri | D91: 109200000
D92: =SUM(D88:D91) -> 3437341500
A94: Total aset + Piutang - Hutang | D94: =D65+D79+D85-D92 -> 1.2159579e+09
A97: CV PUTRA BUMI BERKAH
A98: NERACA
A99: 45903
F101: Selisih = | G101: =D142-D94 -> 14256500
D102: Saldo
A103: Aset | D103: IDR | F103: Rincian =
B104: Bank | F104: Pemasukan
C105: 123-0467834 (BCA) | D105: 40252993 | F105: laba tgl 3 | G105: 13929000
C106: 735-5917878 (BCA) | D106: 44793580 | F106: laba ragi | G106: 327500
C107: 735-5537889 (BCA) | D107: 1.2700003e+08 | G107: =SUM(G105:G106) -> 14256500
C108: 735-5467899 (BCA) | D108: 79767511 | F108: Pengeluaran
C109: 620801016258532 (BRI) | D109: 25000 | G109: 0
C110: 058301001067560 (BRI) | D110: 17233024 | G110: =SUM(G109:G109) -> 0
C111: 058301900009562 (BRI) | D111: 126234429
C112: 058301909090560 (BRI) | D112: 130317 | F112: Pemasukan - pengeluaran | G112: =G107-G110 -> 14256500
B113: Total Bank | D113: =SUM(D105:D112) -> 4.3543689e+08
...

Sheet Deposit
A1: Rincian deposit
A3: Keterangan | B3: Customer | C3: Rekening | D3: Nominal | E3: Tgl masuk | F3: Tgl keluar
A4: deposit lotus 9000x7750 + ongkir | B4: Abah slamet | C4: BCA cv putra | D4: 70965000 | E4: 45643 | F4: 45644 | G4: bri 100jt + bca 113.345.000 17/12
A5: deposit lotus 9000x7750 + ongkir | B5: Abah slamet | C5: BCA cv putra | D5: 42380000 | E5: 45643 | F5: 45646
C6: BRI bisnis | D6: 28585000 | E6: 45643 | F6: 45646
A7: deposit sip 9000x7800 + ongkir | B7: Abah slamet | C7: BRI bisnis | D7: 71415000 | E7: 45643 | F7: 45659
A8: deposit lotus 9000x7500 | B8: Kopti giri | C8: BRI bisnis | D8: 50000000 | E8: 45644 | F8: 45659
C9: BRI bisnis | D9: 17500000 | E9: 45645
A10: hiu 9000x8200 | B10: Bu iin | C10: BCA cv putra | D10: 73800000 | E10: 45650 | F10: 45659
A11: hiu 9000x8200 | B11: Bu iin | C11: BCA cv putra | D11: 73800000 | E11: 45650 | F11: 45668
A12: hiu 9000x8200 | B12: Bu iin | C12: BCA cv putra | D12: 73800000 | E12: 45650 | F12: 45680
A13: hiu 9000x7900 | B13: Ko hadi pohjejer | C13: BCA cv putra | D13: 71100000 | E13: 45652 | F13: 45660
A14: bola 9000x8000 | B14: Ko hadi pohjejer | C14: BCA cv putra | D14: 72000000 | E14: 45652 | F14: 45665
A15: deposit | B15: ATM | C15: BRI bisnis | D15: 10000000 | E15: 45656 | F15: 45659
A16: deposit | B16: Joko wardoyo | C16: BRI bisnis | D16: 40000000 | E16: 45656 | F16: 45659
A17: deposit | B17: Mb linda | C17: BRI bisnis | D17: 50000 | E17: 45657 | F17: 45659
A18: hiu 9000x8200 | B18: Bu yatini ngawi | C18: BCA cv surya | D18: 73800000 | E18: 45658 | F18: 45661
A19: hiu 9000x8500 | B19: Kopti giri | C19: BRI bisnis | D19: 76500000 | E19: 45660 | F19: 45663
A20: ongkir | B20: Pak anwar | C20: BCA cv surya | D20: 1000000 | E20: 45660 | F20: 45661
A21: minyak 185000x800 + ongkir | B21: Mas nanang bjn | C21: BCA individu | D21: 149200000 | E21: 45660 | F21: 45661
... A27: lotus 9000x8300 | B27: Kopti giri | C27: BRI bisnis | D27: 44500000 | E27: 45663 | F27: 45671
D28: 30200000 | E28: 45664 | F28: 45671
A29: ongkir | B29: Abah slamet | C29: BCA cv putra | D29: 2430000 | E29: 45663 | F29: 45664
A30: bagi hasil | B30: Pak iwan | C30: BCA individu | D30: 450000 | E30: 45663 | F30: 45664
A31: panah 8500x8550 | B31: Bu yatini ngawi | C31: BRI bisnis | D31: 72675000 | E31: 45665 | F31: 45666
A32: ongkir | B32: Pak anwar | C32: BCA cv surya | D32: 650000 | E32: 45666 | F32: 45667 | G32: kurang 450rb
A33: tulip 9000x8650 | B33: Abah slamet | C33: BRI bisnis | D33: 77850000 | E33: 45667 | F33: 45673
A34: minyak 185000x800 + ongkir | B34: Mas nanang bjn | C34: BCA individu | D34: 149200000 | E34: 45668 | F34: 45670
A35: sip 9000x8500 | B35: Kopti giri | C35: BRI bisnis | D35: 60000000 | E35: 45668 | F35: 45698
D36: 16500000 | E36: 45670
A37: panah 8500x8600 | B37: Bu yatini ngawi | C37: BRI bisnis | D37: 73100000 | E37: 45671 | F37: 45672
A38: hiu 9000x8550 | B38: Bu yatini ngawi | C38: BCA cv surya | D38: 76950000 | E38: 45671 | F38: 45673
A39: deposit | B39: Bu tutik | C39: BCA cv putra | D39: 2710000 | E39: 45672 | F39: 45677
A40: ongkir | B40: Pak ramin | C40: BCA individu | D40: 1600000 | E40: 45672 | F40: 45674
A41: ongkir | B41: Abah slamet | C41: BRI bisnis | D41: 1215000 | E41: 45667 | F41: 45674
A42: tulip 9000x8300 | B42: Bu iin | C42: BCA cv putra | D42: 74700000 | E42: 45672 | F42: 45682
A43: lotus 9000x8300 | B43: Bu iin | C43: BCA cv putra | D43: 74700000 | E43: 45672 | F43: 45674
A44: tomat/BW 9000x8450 | B44: Kopti giri | C44: BRI bisnis | D44: 39000000 | E44: 45672 | F44: 45688
D45: 37050000 | E45: 45673
A46: sip 9000x8650 | B46: Abah slamet | C46: BCA cv putra | D46: 77850000 | E46: 45673 | F46: 45674
A47: lotus 9000x8950 + ongkir | B47: Pak saiku | C47: BCA cv putra | D47: 81855000 | E47: 45674 | F47: 45677
A48: ongkir | B48: Abah slamet | C48: BCA cv putra | D48: 1215000 | E48: 45673 | F48: 45675
A49: SGR 9000x8500 | B49: Bu iin | C49: BCA cv putra | D49: 76500000 | E49: 45674 | F49: 45677
A50: sip 9000x8500 | B50: Bu iin | C50: BCA cv putra | D50: 76500000 | E50: 45675 | F50: 45689
A51: sip 9000x8650 | B51: Abah slamet | C51: BCA cv putra | D51: 77850000 | E51: 45677 | F51: 45680
A52: sip 9000x8650 | B52: Abah slamet | C52: BCA cv putra | D52: 77850000 | E52: 45677 | F52: 45681 | G52: dibuat bayar tulip tgl 21/1
A53: ongkir | B53: Abah slamet | C53: BCA cv putra | D53: 1215000 | E53: 45677 | F53: 45680
A54: ongkir | B54: Abah slamet | C54: BCA cv putra | D54: 1215000 | E54: 45677 | F54: 45682
A55: deposit | B55: Kopti giri | C55: BRI bisnis | D55: 32000000 | E55: 45677 | F55: 45678
A56: ragi | B56: Bu kasmi | C56: BRI bisnis | D56: 3125000 | E56: 45678 | F56: 45679
A57: SGR 9000x8600 | B57: Bu iin | C57: BCA cv putra | D57: 79200000 | E57: 45679 | F57: 45687
A58: ongkir | B58: Abah slamet | C58: BCA cv putra | D58: 1215000 | E58: 45681 | F58: 45682
A59: tulip 9000x8700 | B59: Abah slamet | C59: BCA cv putra | D59: 78300000 | E59: 45681 | F59: 45682
A60: ongkir | B60: Abah slamet | C60: BCA cv putra | D60: 1215000 | E60: 45681 | F60: 45682
A61: tulip 10000x8800 | B61: Pak yanto | C61: BCA cv putra | D61: 10000000 | E61: 45681 | F61: 45777
A62: sip 9000x8350 | B62: Pak jum | C62: BRI bisnis | D62: 75150000 | E62: 45681 | F62: 45682
A63: ragi | B63: Mb ida | C63: BCA cv surya | D63: 80000 | E63: 45682 | F63: 45687
A64: ongkir | B64: Pak anwar | C64: BCA cv surya | D64: 1000000 | E64: 45685 | F64: 45687
... A80: selendang 9000x8050 | B80: Kopti giri | C80: BRI bisnis | D80: 16000000 | E80: 45714 | F80: 45728
A81: deposit | B81: Fidiya Hurhayati S | C81: BCA cv surya | D81: 76050000 | E81: 45715 | F81: 45716 | G81: pak juwari
A82: deposit | C82: BRI bisnis | D82: 75465000 | E82: 45719 | F82: 45720 | G82: abah slamet
A83: selendang 9000x8050 | B83: Kopti giri | C83: BRI bisnis | D83: 31450000 | E83: 45720 | F83: 45728
A84: deposit | B84: Pak yanto | C84: BCA cv putra | D84: 8450000 | E84: 45722 | F84: 45731
A85: ongkir | B85: Ustad muh | C85: BRI bisnis | D85: 1400000 | E85: 45724 | F85: 45726
A86: deposit | C86: BCA cv putra | D86: 87500000 | E86: 45729 | F86: 45730 | G86: bu kusaimah
A87: sip 9000x8300 | B87: Kopti giri | C87: BRI bisnis | D87: 60000000 | E87: 45731 | F87: 45738
A88: bola 8500x8725 | B88: Abah dori | C88: BCA cv putra | D88: 74162500 | E88: 45731 | F88: 45736
A89: sip 9000x8300 | B89: Kopti giri | C89: BRI bisnis | D89: 14700000 | E89: 45734 | F89: 45738
A90: panah 9000x8475 | B90: Bu iin | C90: BCA cv putra | D90: 76275000 | E90: 45736 | F90: 45772
A91: panah 9000x8475 | B91: Bu iin | C91: BCA cv putra | D91: 76275000 | E91: 45736 | F91: 45780
A92: panah 9000x8475 | B92: Bu iin | C92: BCA cv putra | D92: 76275000 | E92: 45736 | F92: 45787
A93: panah 10000x8450 | B93: Kopti sepanjang | C93: BCA cv putra | D93: 84500000 | E93: 45736 | F93: 45738
A94: sip 9000x8250 | B94: Tejo mojokerto | C94: BCA cv putra | D94: 74250000 | E94: 45736 | F94: 45737
A95: sip 9000x8450 + ongkir | B95: Bu yatini ngawi | C95: BRI bisnis | D95: 76050000 | E95: 45737 | F95: 45738
A96: sip 9000x8450 + ongkir | B96: Bu yatini ngawi | C96: BRI bisnis | D96: 76050000 | E96: 45737 | F96: 45738
A97: deposit | B97: Bu tutik | C97: BCA cv putra | D97: 80000000 | E97: 45737 | F97: 45740
A98: hiu 9000x8650 | B98: Pak jum | C98: BRI bisnis | D98: 77850000 | E98: 45737 | F98: 45740
... A117: hiu 18000x9100 | B117: Bu yatini | C117: BRI bisnis | D117: 81900000 | E117: 45750 | F117: 45757
D118: 18100000 | F118: 45759
A119: sip 9000x8600 | B119: Bu yatini | C119: BRI bisnis | D119: 77400000 | E119: 45750 | F119: 45751
A120: panah 8500x8550 | B120: Bu yatini | C120: BRI bisnis | D120: 72675000 | E120: 45750 | F120: 45751
A121: bagi hasil | B121: Pak iwan | C121: BCA individu | D121: 450000 | E121: 45751 | F121: 45755
A122: bagi hasil | B122: Pak iwan | C122: BCA individu | D122: 450000 | E122: 45754 | F122: 45755
A123: hiu 9000x8800 | B123: Tejo mojokerto | C123: BCA cv putra | D123: 79200000 | E123: 45751 | F123: 45761
A124: hiu 9000x8800 | D124: 20800000 | F124: 45769
A125: tulip 9000x8850 | B125: Bu iin | C125: BCA cv putra | D125: 79650000 | E125: 45755 | F125: 45762
A126: hiu 9000x9100 | B126: Bu iin | C126: BCA cv putra | D126: 81900000 | E126: 45756 | F126: 45757
A127: tomat/BW 9000x8850 | B127: Bu iin | C127: BCA cv putra | D127: 79650000 | E127: 45756 | F127: 45768
A128: tomat/BW 9000x8850 | B128: Bu iin | C128: BCA cv putra | D128: 79650000 | E128: 45756 | F128: 45776
A129: hiu 18000x9100 | B129: Bu yatini | C129: BCA cv surya | D129: 63800000 | E129: 45756 | F129: 45759
A130: panah 8500x9150 | B130: Bu yatini | C130: BRI bisnis | D130: 77775000 | E130: 45756 | F130: 45758
A131: tomat/BW 9000x8600 | B131: Kopti giri | C131: BRI bisnis | D131: 39400000 | E131: 45756 | F131: 45763
A132: hiu 9000x9150 | B132: Abah dori | C132: BCA cv surya | D132: 73350000 | E132: 45756 | F132: 45758
A133: tulip 9000x8850 + ongkir | B133: Abah slamet | C133: BCA cv putra | D133: 80865000 | E133: 45757 | F133: 45758
A134: tulip 9000x8850 | B134: Abah slamet | C134: BCA cv putra | D134: 79650000 | E134: 45757 | F134: 45755
A135: hiu 9000x8425 | B135: Abah slamet | C135: BCA cv putra | D135: 74175000 | E135: 45743 | F135: 45758
A136: tomat/BW 9000x8850 | B136: Bu iin | C136: BCA cv putra | D136: 79650000 | E136: 45757 | F136: 45782
... A173: tulip 9000x9100 + ongkir | B173: Abah slamet | C173: BRI bisnis | D173: 22950000 | E173: 45769 | F173: 45785
C174: BCA cv putra | D174: 60165000 | E174: 45769 | F174: 45785
A175: tulip 9000x9100 + ongkir | B175: Abah slamet | C175: BCA cv putra | D175: 83115000 | E175: 45769 | F175: 45786
...

Sheet Audit mingguan
A1: CV PUTRA BUMI BERKAH
A2: PERHITUNGAN KEUANGAN
A3: 45549
E5: Rincian pinjaman BRI =
C6: Saldo
A7: Aset | C7: IDR | E7: Pelunasan agrico tgl 31/5 | F7: 2000000000
E8: Pelunasan pinjaman bu tutik oktober | F8: 500000000
B9: Saldo bank | C9: 1.7547283e+09 | E9: Deposit saldo | F9: 335000000
B10: Aset bergerak | C10: 1992000000 | E10: Biaya notaris + pencairan BRI | F10: 83000000
B11: Piutang toko | C11: 490025000 | F11: =SUM(F7:F10) -> 2918000000
B12: Piutang all customer + ragi | C12: 1962203500
B13: Stock ragi 110karton | C13: 66275000 | E13: Rincian akhir pinjaman BRI =
B14: Pak nanok + pak ozi | C14: 55000000 | E14: Pemasukan
C15: =SUM(C9:C14) -> 6.3202318e+09 | E15: Sisa modal dari BRI | F15: 1.6105943e+09
E16: Laba jan-agust | F16: 793614325
A17: Hutang | F17: =SUM(F15:F16) -> 2.4042086e+09
B18: PT Agrico International | C18: 2341775000 | E18: Pengeluaran
B19: PT JPM-ADM Indonesia | C19: 1223062500 | E19: Juni - sept 14/9 | F19: 1770286500
B20: PT Terus Makmur Mandiri | C20: 144800000 | F20: =F19 -> 1770286500
B21: Bu tutik | C21: 500000000
B22: Mb retno | C22: 500000000 | E22: Pemasukan - pengeluaran | F22: =F17-F20 -> 6.3392211e+08
C23: =SUM(C18:C22) -> 4709637500
A25: Total aset + Piutang - Hutang | C25: =C15-C23 -> 1.6105943e+09
